pyftpdlibsqladdon/__init__.py
pyftpdlibsqladdon/client.py
pyftpdlibsqladdon/dummysqlauthorizer.py
pyftpdlibsqladdon-0.1.1.dist-info/LICENSE
pyftpdlibsqladdon-0.1.1.dist-info/METADATA
pyftpdlibsqladdon-0.1.1.dist-info/WHEEL
pyftpdlibsqladdon-0.1.1.dist-info/top_level.txt
pyftpdlibsqladdon-0.1.1.dist-info/RECORD
