Metadata-Version: 2.1
Name: pyftpdlibsqladdon
Version: 0.1.1
Summary: Module for implementing FTP users in pyftpdlib through a SQL server
Home-page: https://github.com/BookmanTasty/pyftpdlibsqladdon
Author: Cesar Leyva
Author-email: cesarleyva@leyvadev.com
License: MIT
Keywords: ftp,ftps,server,ftpd,daemon,python,ssl,sendfile,asynchronous,nonblocking,eventdriven,sql
Platform: UNKNOWN
Classifier: Intended Audience :: Developers
Classifier: License :: OSI Approved :: MIT License
Classifier: Programming Language :: Python
Classifier: Programming Language :: Python :: 3
Classifier: Programming Language :: Python :: 3.6
Classifier: Programming Language :: Python :: 3.7
Classifier: Programming Language :: Python :: 3.8
Classifier: Programming Language :: Python :: 3.9
Classifier: Programming Language :: Python :: 3.10
Classifier: Operating System :: OS Independent
License-File: LICENSE
Requires-Dist: pyftpdlib
Requires-Dist: mysql-connector-python
